MANIFEST.in
README.rst
setup.py
src/ua2/__init__.py
src/ua2.jsondoc.egg-info/PKG-INFO
src/ua2.jsondoc.egg-info/SOURCES.txt
src/ua2.jsondoc.egg-info/dependency_links.txt
src/ua2.jsondoc.egg-info/eager_resources.txt
src/ua2.jsondoc.egg-info/namespace_packages.txt
src/ua2.jsondoc.egg-info/not-zip-safe
src/ua2.jsondoc.egg-info/top_level.txt
src/ua2/jsondoc/__init__.py
src/ua2/jsondoc/decoder.py
src/ua2/jsondoc/encoder.py
src/ua2/jsondoc/handler.py
src/ua2/jsondoc/manager.py