Metadata-Version: 1.1
Name: ua2.jsondoc
Version: 0.3.2
Summary: Library for serialize django model header to json dictionary
Home-page: https://bitbucket.org/sdh-llc/ua2.jsondoc
Author: Viacheslav Vic Bukhantsov
Author-email: vic@ua2crm.com
License: BSD License
Platform: UNKNOWN
Classifier: Development Status :: 4 - Beta
Classifier: Framework :: Django
Classifier: Programming Language :: Python :: 2
Classifier: Programming Language :: Python :: 3
Classifier: Topic :: Software Development :: Libraries
